glorpen_config-2.2.0-py3.6-nspkg.pth
glorpen/config/__init__.py
glorpen/config/exceptions.py
glorpen/config/loaders.py
glorpen/config/tests.py
glorpen/config/fields/__init__.py
glorpen/config/fields/base.py
glorpen/config/fields/log.py
glorpen/config/fields/simple.py
glorpen/config/fields/version.py
glorpen_config-2.2.0.dist-info/METADATA
glorpen_config-2.2.0.dist-info/WHEEL
glorpen_config-2.2.0.dist-info/namespace_packages.txt
glorpen_config-2.2.0.dist-info/top_level.txt
glorpen_config-2.2.0.dist-info/RECORD
